{"type":"published","id":"bs-vscode","name":"bs-vscode","version":"0.1.0","description":"Visual Studio Code extension API bindings for BuckleScript","author":"glennsl","license":"MIT","keywords":["vscode","extension","bindings","bucklescript"],"body":"# bs-vscode\n\nIncomplete Visual Studio Code extension API bindings for BuckleScript\n\n## Usage\n\nSee the [reasonable-vscode-starter](https://github.com/glennsl/reasonable-vscode-starter) project as an example.","analyzed":"2017-12-23T15:26:53.286Z","updated":"2017-12-23T15:26:53.286Z","stars":2,"score":0.46157685999651393,"quality":0.36284629848253197,"popularity":0.024712616353754605,"maintenance":0.9830672992226863,"homepageUrl":"https://github.com/glennsl/bs-vscode#readme","repositoryUrl":"https://github.com/glennsl/bs-vscode","npmUrl":"https://www.npmjs.com/package/bs-vscode","issuesUrl":"https://github.com/glennsl/bs-vscode/issues","docsUrl":null}